{
  "title": "You Got It",
  "date": "2025-12-26T05:00:00.000Z",
  "link": [
    {
      "url": "https://youtube.com/playlist?list=OLAK5uy_kIfM1eB0_zRZJMrsxxAStr9WQDfj5PLeY&si=2d9mkqIFcg4qN_Sh",
      "provider": "youtube"
    },
    {
      "url": "https://music.apple.com/us/album/you-got-it/1864466136?i=1864466137",
      "provider": "apple music"
    },
    {
      "url": "https://open.spotify.com/album/2kcBXRhEdyHZ6ZmRPd8HYT?si=Lr-NyzNGQBuBkE1qAKogTg",
      "provider": "spotify"
    }
  ],
  "description": "“You Got It” is a confident, feel-good track built around reassurance and mutual attraction. The song leans into a smooth, modern groove, pairing laid-back energy with lyrics that affirm trust, desire, and emotional certainty. It’s the kind of song that feels effortless and self-assured, like a quiet promise delivered with style.\n"
}